dhx_utils_aws/__init__.py
dhx_utils_aws/events.py
dhx_utils_aws/ingestion.py
dhx_utils_aws/main.py
dhx_utils_aws/s3.py
dhx_utils_aws-1.2.2b212+b6be8bb8.dist-info/METADATA
dhx_utils_aws-1.2.2b212+b6be8bb8.dist-info/WHEEL
dhx_utils_aws-1.2.2b212+b6be8bb8.dist-info/entry_points.txt
dhx_utils_aws-1.2.2b212+b6be8bb8.dist-info/top_level.txt
dhx_utils_aws-1.2.2b212+b6be8bb8.dist-info/RECORD
