Metadata-Version: 2.1
Name: dhx-utils-aws
Version: 1.2.2b212
Summary: DataHex Utility for AWS
Home-page: https://github.com/rozettatechnology/datahex-utils
Author: RoZetta Technology
Author-email: developers@rozettatechnology.com
License: UNKNOWN
Platform: UNKNOWN
Classifier: Development Status :: 3 - Alpha
Classifier: Environment :: Console
Classifier: Intended Audience :: Developers
Classifier: License :: Other/Proprietary License
Classifier: Natural Language :: English
Classifier: Operating System :: Unix
Classifier: Programming Language :: Python
Classifier: Topic :: Software Development
Requires-Dist: boto3 (>=1.16)
Requires-Dist: botocore (>=1.19)
Requires-Dist: simplejson (>=3.17)
Requires-Dist: dhx-audit-client (<1.1,>=1.0.11b)
Requires-Dist: dhx-utils-lib (<2.0.0,>=1.0.0b)
